oassign/__init__.py
oassign/oassign.py
oassign/to_ok.py
test/__init__.py
test/test_conversion.py
otter_assign-0.0.2.dist-info/LICENSE
otter_assign-0.0.2.dist-info/METADATA
otter_assign-0.0.2.dist-info/WHEEL
otter_assign-0.0.2.dist-info/entry_points.txt
otter_assign-0.0.2.dist-info/top_level.txt
otter_assign-0.0.2.dist-info/RECORD
