Metadata-Version: 2.1
Name: otter-assign
Version: 0.0.2
Summary: Jupyter notebook assignment formatting and distribution for Otter-Grader
Home-page: https://github.com/ucbds-infra/otter-assign
Author: Chris Pyles
Author-email: cpyles@berkeley.edu
License: UNKNOWN
Platform: UNKNOWN
Classifier: Programming Language :: Python :: 3
Classifier: License :: OSI Approved :: MIT License
Classifier: Operating System :: OS Independent
Requires-Dist: pyyaml
Requires-Dist: nbformat
Requires-Dist: ipython
Requires-Dist: nbconvert
Requires-Dist: tqdm
Requires-Dist: setuptools
Requires-Dist: otter-grader
Requires-Dist: pandas
